Excalidraw_Interface/LICENSE
Excalidraw_Interface/__init__.py
Excalidraw_Interface/defaults.py
Excalidraw_Interface/primitives.py
Excalidraw_Interface/sketch_builder.py
Excalidraw_Interface/examples/advanced_groups.py
Excalidraw_Interface/examples/flowchart.py
Excalidraw_Interface/fonts/Assistant-VariableFont.ttf
Excalidraw_Interface/fonts/CascadiaCode.ttf
Excalidraw_Interface/fonts/Virgil.ttf
excalidraw_interface-0.1.3.dist-info/licenses/LICENSE
excalidraw_interface-0.1.3.dist-info/METADATA
excalidraw_interface-0.1.3.dist-info/WHEEL
excalidraw_interface-0.1.3.dist-info/top_level.txt
excalidraw_interface-0.1.3.dist-info/RECORD
