Metadata-Version: 2.4
Name: Excalidraw_Interface
Version: 0.1.3
Summary: Create excalidraw drawings with python
Home-page: https://github.com/RobertJN64/Excalidraw_Interface
Author: Robert Nies
Author-email: robertjnies@gmail.com
License: MIT
Classifier: Programming Language :: Python
Classifier: Programming Language :: Python :: 3
Classifier: Programming Language :: Python :: 3 :: Only
Classifier: Programming Language :: Python :: 3.10
Classifier: Programming Language :: Python :: 3.11
Classifier: Programming Language :: Python :: 3.12
Classifier: Programming Language :: Python :: 3.13
Classifier: Programming Language :: Python :: 3.14
Requires-Python: >=3.10
License-File: LICENSE
Requires-Dist: pillow
Dynamic: license-file
